[
  {
    "Year": 1985,
    "Method": "colley",
    "Weight": "gaussian",
    "Conference": "PCAA",
    "Team": "Nevada-Las Vegas",
    "Rating": 0.833682991123342,
    "Rank": 1
  },
  {
    "Year": 1985,
    "Method": "colley",
    "Weight": "gaussian",
    "Conference": "PCAA",
    "Team": "Fresno State",
    "Rating": 0.6730456814984873,
    "Rank": 2
  },
  {
    "Year": 1985,
    "Method": "colley",
    "Weight": "gaussian",
    "Conference": "PCAA",
    "Team": "Cal State Fullerton",
    "Rating": 0.6444715573883186,
    "Rank": 3
  },
  {
    "Year": 1985,
    "Method": "colley",
    "Weight": "gaussian",
    "Conference": "PCAA",
    "Team": "San Jose State",
    "Rating": 0.5987062081153507,
    "Rank": 4
  },
  {
    "Year": 1985,
    "Method": "colley",
    "Weight": "gaussian",
    "Conference": "PCAA",
    "Team": "Utah State",
    "Rating": 0.5367917288433437,
    "Rank": 5
  },
  {
    "Year": 1985,
    "Method": "colley",
    "Weight": "gaussian",
    "Conference": "PCAA",
    "Team": "UC Irvine",
    "Rating": 0.4530581535130283,
    "Rank": 6
  },
  {
    "Year": 1985,
    "Method": "colley",
    "Weight": "gaussian",
    "Conference": "PCAA",
    "Team": "UC Santa Barbara",
    "Rating": 0.3866693187610189,
    "Rank": 7
  },
  {
    "Year": 1985,
    "Method": "colley",
    "Weight": "gaussian",
    "Conference": "PCAA",
    "Team": "Pacific",
    "Rating": 0.3250474573920741,
    "Rank": 8
  },
  {
    "Year": 1985,
    "Method": "colley",
    "Weight": "gaussian",
    "Conference": "PCAA",
    "Team": "Long Beach State",
    "Rating": 0.2953737454393254,
    "Rank": 9
  },
  {
    "Year": 1985,
    "Method": "colley",
    "Weight": "gaussian",
    "Conference": "PCAA",
    "Team": "New Mexico State",
    "Rating": 0.2531531579257128,
    "Rank": 10
  }
]