[
  {
    "Year": 1991,
    "Method": "colley",
    "Weight": "linear",
    "Conference": "Ivy",
    "Team": "Princeton",
    "Rating": 0.8713613402425588,
    "Rank": 1
  },
  {
    "Year": 1991,
    "Method": "colley",
    "Weight": "linear",
    "Conference": "Ivy",
    "Team": "Yale",
    "Rating": 0.6304379829720411,
    "Rank": 2
  },
  {
    "Year": 1991,
    "Method": "colley",
    "Weight": "linear",
    "Conference": "Ivy",
    "Team": "Pennsylvania",
    "Rating": 0.4600804941791041,
    "Rank": 3
  },
  {
    "Year": 1991,
    "Method": "colley",
    "Weight": "linear",
    "Conference": "Ivy",
    "Team": "Brown",
    "Rating": 0.4542237862098991,
    "Rank": 4
  },
  {
    "Year": 1991,
    "Method": "colley",
    "Weight": "linear",
    "Conference": "Ivy",
    "Team": "Cornell",
    "Rating": 0.4498900100271846,
    "Rank": 5
  },
  {
    "Year": 1991,
    "Method": "colley",
    "Weight": "linear",
    "Conference": "Ivy",
    "Team": "Harvard",
    "Rating": 0.3830528017436101,
    "Rank": 6
  },
  {
    "Year": 1991,
    "Method": "colley",
    "Weight": "linear",
    "Conference": "Ivy",
    "Team": "Dartmouth",
    "Rating": 0.377028705358068,
    "Rank": 7
  },
  {
    "Year": 1991,
    "Method": "colley",
    "Weight": "linear",
    "Conference": "Ivy",
    "Team": "Columbia",
    "Rating": 0.3739248792675334,
    "Rank": 8
  }
]