[
  {
    "Year": 1992,
    "Method": "colley",
    "Weight": "gaussian",
    "Conference": "NEC",
    "Team": "Robert Morris",
    "Rating": 0.7344931096275114,
    "Rank": 1
  },
  {
    "Year": 1992,
    "Method": "colley",
    "Weight": "gaussian",
    "Conference": "NEC",
    "Team": "Monmouth",
    "Rating": 0.5851774061865898,
    "Rank": 2
  },
  {
    "Year": 1992,
    "Method": "colley",
    "Weight": "gaussian",
    "Conference": "NEC",
    "Team": "Fairleigh Dickinson",
    "Rating": 0.5596315271057343,
    "Rank": 3
  },
  {
    "Year": 1992,
    "Method": "colley",
    "Weight": "gaussian",
    "Conference": "NEC",
    "Team": "St. Francis (NY)",
    "Rating": 0.5504947919650123,
    "Rank": 4
  },
  {
    "Year": 1992,
    "Method": "colley",
    "Weight": "gaussian",
    "Conference": "NEC",
    "Team": "Wagner",
    "Rating": 0.5068752539110226,
    "Rank": 5
  },
  {
    "Year": 1992,
    "Method": "colley",
    "Weight": "gaussian",
    "Conference": "NEC",
    "Team": "Long Island University",
    "Rating": 0.4720873764968388,
    "Rank": 6
  },
  {
    "Year": 1992,
    "Method": "colley",
    "Weight": "gaussian",
    "Conference": "NEC",
    "Team": "Saint Francis (PA)",
    "Rating": 0.4377423378185912,
    "Rank": 7
  },
  {
    "Year": 1992,
    "Method": "colley",
    "Weight": "gaussian",
    "Conference": "NEC",
    "Team": "Marist",
    "Rating": 0.4076730913055748,
    "Rank": 8
  },
  {
    "Year": 1992,
    "Method": "colley",
    "Weight": "gaussian",
    "Conference": "NEC",
    "Team": "Mount St. Mary's",
    "Rating": 0.2458251055831256,
    "Rank": 9
  }
]