[
  {
    "Year": 1992,
    "Method": "colley",
    "Weight": "constant",
    "Conference": "Big West",
    "Team": "Nevada-Las Vegas",
    "Rating": 0.909090909090909,
    "Rank": 1
  },
  {
    "Year": 1992,
    "Method": "colley",
    "Weight": "constant",
    "Conference": "Big West",
    "Team": "New Mexico State",
    "Rating": 0.676870681885746,
    "Rank": 2
  },
  {
    "Year": 1992,
    "Method": "colley",
    "Weight": "constant",
    "Conference": "Big West",
    "Team": "UC Santa Barbara",
    "Rating": 0.6415210629643647,
    "Rank": 3
  },
  {
    "Year": 1992,
    "Method": "colley",
    "Weight": "constant",
    "Conference": "Big West",
    "Team": "Long Beach State",
    "Rating": 0.5881452371749039,
    "Rank": 4
  },
  {
    "Year": 1992,
    "Method": "colley",
    "Weight": "constant",
    "Conference": "Big West",
    "Team": "Utah State",
    "Rating": 0.5207872040593485,
    "Rank": 5
  },
  {
    "Year": 1992,
    "Method": "colley",
    "Weight": "constant",
    "Conference": "Big West",
    "Team": "Pacific",
    "Rating": 0.4781056933650193,
    "Rank": 6
  },
  {
    "Year": 1992,
    "Method": "colley",
    "Weight": "constant",
    "Conference": "Big West",
    "Team": "Cal State Fullerton",
    "Rating": 0.4386150103119522,
    "Rank": 7
  },
  {
    "Year": 1992,
    "Method": "colley",
    "Weight": "constant",
    "Conference": "Big West",
    "Team": "Fresno State",
    "Rating": 0.3555161166037279,
    "Rank": 8
  },
  {
    "Year": 1992,
    "Method": "colley",
    "Weight": "constant",
    "Conference": "Big West",
    "Team": "UC Irvine",
    "Rating": 0.2549844481803908,
    "Rank": 9
  },
  {
    "Year": 1992,
    "Method": "colley",
    "Weight": "constant",
    "Conference": "Big West",
    "Team": "San Jose State",
    "Rating": 0.1363636363636362,
    "Rank": 10
  }
]