[
  {
    "Year": 1993,
    "Method": "massey",
    "Weight": "logarithmic",
    "Conference": "ACC",
    "Team": "North Carolina",
    "Rating": 12.932138245265884,
    "Rank": 1
  },
  {
    "Year": 1993,
    "Method": "massey",
    "Weight": "logarithmic",
    "Conference": "ACC",
    "Team": "Duke",
    "Rating": 6.862225164945079,
    "Rank": 2
  },
  {
    "Year": 1993,
    "Method": "massey",
    "Weight": "logarithmic",
    "Conference": "ACC",
    "Team": "Wake Forest",
    "Rating": 2.443367592252033,
    "Rank": 3
  },
  {
    "Year": 1993,
    "Method": "massey",
    "Weight": "logarithmic",
    "Conference": "ACC",
    "Team": "Florida State",
    "Rating": 2.021599610651538,
    "Rank": 4
  },
  {
    "Year": 1993,
    "Method": "massey",
    "Weight": "logarithmic",
    "Conference": "ACC",
    "Team": "Georgia Tech",
    "Rating": 1.4810881236268192,
    "Rank": 5
  },
  {
    "Year": 1993,
    "Method": "massey",
    "Weight": "logarithmic",
    "Conference": "ACC",
    "Team": "Virginia",
    "Rating": -0.3769542544187438,
    "Rank": 6
  },
  {
    "Year": 1993,
    "Method": "massey",
    "Weight": "logarithmic",
    "Conference": "ACC",
    "Team": "Clemson",
    "Rating": -3.724960348916044,
    "Rank": 7
  },
  {
    "Year": 1993,
    "Method": "massey",
    "Weight": "logarithmic",
    "Conference": "ACC",
    "Team": "Maryland",
    "Rating": -8.850959189637203,
    "Rank": 8
  },
  {
    "Year": 1993,
    "Method": "massey",
    "Weight": "logarithmic",
    "Conference": "ACC",
    "Team": "NC State",
    "Rating": -12.787544943769362,
    "Rank": 9
  }
]