[
  {
    "Year": 1995,
    "Method": "colley",
    "Weight": "logarithmic",
    "Conference": "OVC",
    "Team": "Murray State",
    "Rating": 0.6955098442121482,
    "Rank": 1
  },
  {
    "Year": 1995,
    "Method": "colley",
    "Weight": "logarithmic",
    "Conference": "OVC",
    "Team": "Tennessee State",
    "Rating": 0.583896414985994,
    "Rank": 2
  },
  {
    "Year": 1995,
    "Method": "colley",
    "Weight": "logarithmic",
    "Conference": "OVC",
    "Team": "Morehead State",
    "Rating": 0.5494262133125926,
    "Rank": 3
  },
  {
    "Year": 1995,
    "Method": "colley",
    "Weight": "logarithmic",
    "Conference": "OVC",
    "Team": "Austin Peay",
    "Rating": 0.5435752554726642,
    "Rank": 4
  },
  {
    "Year": 1995,
    "Method": "colley",
    "Weight": "logarithmic",
    "Conference": "OVC",
    "Team": "Tennessee Tech",
    "Rating": 0.5156897853486154,
    "Rank": 5
  },
  {
    "Year": 1995,
    "Method": "colley",
    "Weight": "logarithmic",
    "Conference": "OVC",
    "Team": "Southeast Missouri State",
    "Rating": 0.4691676633129732,
    "Rank": 6
  },
  {
    "Year": 1995,
    "Method": "colley",
    "Weight": "logarithmic",
    "Conference": "OVC",
    "Team": "Eastern Kentucky",
    "Rating": 0.4330079078529404,
    "Rank": 7
  },
  {
    "Year": 1995,
    "Method": "colley",
    "Weight": "logarithmic",
    "Conference": "OVC",
    "Team": "Tennessee-Martin",
    "Rating": 0.3649498728749252,
    "Rank": 8
  },
  {
    "Year": 1995,
    "Method": "colley",
    "Weight": "logarithmic",
    "Conference": "OVC",
    "Team": "Middle Tennessee",
    "Rating": 0.3447770426271497,
    "Rank": 9
  }
]