[
  {
    "Year": 1997,
    "Method": "colley",
    "Weight": "logarithmic",
    "Conference": "A-10",
    "Team": "Saint Joseph's",
    "Rating": 0.8037239662807094,
    "Rank": 1
  },
  {
    "Year": 1997,
    "Method": "colley",
    "Weight": "logarithmic",
    "Conference": "A-10",
    "Team": "Rhode Island",
    "Rating": 0.7169821207551429,
    "Rank": 2
  },
  {
    "Year": 1997,
    "Method": "colley",
    "Weight": "logarithmic",
    "Conference": "A-10",
    "Team": "Xavier",
    "Rating": 0.7040885032520413,
    "Rank": 3
  },
  {
    "Year": 1997,
    "Method": "colley",
    "Weight": "logarithmic",
    "Conference": "A-10",
    "Team": "Temple",
    "Rating": 0.6374868237145865,
    "Rank": 4
  },
  {
    "Year": 1997,
    "Method": "colley",
    "Weight": "logarithmic",
    "Conference": "A-10",
    "Team": "Massachusetts",
    "Rating": 0.6365467322182576,
    "Rank": 5
  },
  {
    "Year": 1997,
    "Method": "colley",
    "Weight": "logarithmic",
    "Conference": "A-10",
    "Team": "George Washington",
    "Rating": 0.5123199066836522,
    "Rank": 6
  },
  {
    "Year": 1997,
    "Method": "colley",
    "Weight": "logarithmic",
    "Conference": "A-10",
    "Team": "Virginia Tech",
    "Rating": 0.4249426582474299,
    "Rank": 7
  },
  {
    "Year": 1997,
    "Method": "colley",
    "Weight": "logarithmic",
    "Conference": "A-10",
    "Team": "St. Bonaventure",
    "Rating": 0.3861122116376849,
    "Rank": 8
  },
  {
    "Year": 1997,
    "Method": "colley",
    "Weight": "logarithmic",
    "Conference": "A-10",
    "Team": "Dayton",
    "Rating": 0.369145976608805,
    "Rank": 9
  },
  {
    "Year": 1997,
    "Method": "colley",
    "Weight": "logarithmic",
    "Conference": "A-10",
    "Team": "La Salle",
    "Rating": 0.3245007243374864,
    "Rank": 10
  },
  {
    "Year": 1997,
    "Method": "colley",
    "Weight": "logarithmic",
    "Conference": "A-10",
    "Team": "Duquesne",
    "Rating": 0.3199588186052001,
    "Rank": 11
  },
  {
    "Year": 1997,
    "Method": "colley",
    "Weight": "logarithmic",
    "Conference": "A-10",
    "Team": "Fordham",
    "Rating": 0.1641915576590046,
    "Rank": 12
  }
]