[
  {
    "Year": 2007,
    "Method": "massey",
    "Weight": "linear",
    "Conference": "MVC",
    "Team": "Creighton",
    "Rating": 7.897953926676713,
    "Rank": 1
  },
  {
    "Year": 2007,
    "Method": "massey",
    "Weight": "linear",
    "Conference": "MVC",
    "Team": "Southern Illinois",
    "Rating": 5.42255078484499,
    "Rank": 2
  },
  {
    "Year": 2007,
    "Method": "massey",
    "Weight": "linear",
    "Conference": "MVC",
    "Team": "Missouri State",
    "Rating": 4.916422974060363,
    "Rank": 3
  },
  {
    "Year": 2007,
    "Method": "massey",
    "Weight": "linear",
    "Conference": "MVC",
    "Team": "Bradley",
    "Rating": 1.3327608102155577,
    "Rank": 4
  },
  {
    "Year": 2007,
    "Method": "massey",
    "Weight": "linear",
    "Conference": "MVC",
    "Team": "Wichita State",
    "Rating": -0.6426101916441951,
    "Rank": 5
  },
  {
    "Year": 2007,
    "Method": "massey",
    "Weight": "linear",
    "Conference": "MVC",
    "Team": "Northern Iowa",
    "Rating": -1.0168205219294526,
    "Rank": 6
  },
  {
    "Year": 2007,
    "Method": "massey",
    "Weight": "linear",
    "Conference": "MVC",
    "Team": "Illinois State",
    "Rating": -2.67799408508626,
    "Rank": 7
  },
  {
    "Year": 2007,
    "Method": "massey",
    "Weight": "linear",
    "Conference": "MVC",
    "Team": "Evansville",
    "Rating": -3.3116218783621094,
    "Rank": 8
  },
  {
    "Year": 2007,
    "Method": "massey",
    "Weight": "linear",
    "Conference": "MVC",
    "Team": "Drake",
    "Rating": -3.54966339746631,
    "Rank": 9
  },
  {
    "Year": 2007,
    "Method": "massey",
    "Weight": "linear",
    "Conference": "MVC",
    "Team": "Indiana State",
    "Rating": -8.370978421309331,
    "Rank": 10
  }
]