[
  {
    "Year": 2016,
    "Method": "massey",
    "Weight": "sigmoid",
    "Conference": "",
    "Team": "Michigan State",
    "Rating": 26.16190050067497,
    "Rank": 1
  },
  {
    "Year": 2016,
    "Method": "massey",
    "Weight": "sigmoid",
    "Conference": "",
    "Team": "Kansas",
    "Rating": 25.62691303609965,
    "Rank": 2
  },
  {
    "Year": 2016,
    "Method": "massey",
    "Weight": "sigmoid",
    "Conference": "",
    "Team": "North Carolina",
    "Rating": 24.432790994675837,
    "Rank": 3
  },
  {
    "Year": 2016,
    "Method": "massey",
    "Weight": "sigmoid",
    "Conference": "",
    "Team": "Virginia",
    "Rating": 23.735061852414766,
    "Rank": 4
  },
  {
    "Year": 2016,
    "Method": "massey",
    "Weight": "sigmoid",
    "Conference": "",
    "Team": "Kentucky",
    "Rating": 23.5235444334006,
    "Rank": 5
  },
  {
    "Year": 2016,
    "Method": "massey",
    "Weight": "sigmoid",
    "Conference": "",
    "Team": "Oregon",
    "Rating": 22.126447468089708,
    "Rank": 6
  },
  {
    "Year": 2016,
    "Method": "massey",
    "Weight": "sigmoid",
    "Conference": "",
    "Team": "West Virginia",
    "Rating": 21.64759099857239,
    "Rank": 7
  },
  {
    "Year": 2016,
    "Method": "massey",
    "Weight": "sigmoid",
    "Conference": "",
    "Team": "Arizona",
    "Rating": 21.62637283820496,
    "Rank": 8
  },
  {
    "Year": 2016,
    "Method": "massey",
    "Weight": "sigmoid",
    "Conference": "",
    "Team": "Purdue",
    "Rating": 21.52098142330372,
    "Rank": 9
  },
  {
    "Year": 2016,
    "Method": "massey",
    "Weight": "sigmoid",
    "Conference": "",
    "Team": "Indiana",
    "Rating": 20.8563851652956,
    "Rank": 10
  },
  {
    "Year": 2016,
    "Method": "massey",
    "Weight": "sigmoid",
    "Conference": "",
    "Team": "Villanova",
    "Rating": 20.55508102037382,
    "Rank": 11
  },
  {
    "Year": 2016,
    "Method": "massey",
    "Weight": "sigmoid",
    "Conference": "",
    "Team": "Utah",
    "Rating": 19.52097073949914,
    "Rank": 12
  },
  {
    "Year": 2016,
    "Method": "massey",
    "Weight": "sigmoid",
    "Conference": "",
    "Team": "Oklahoma",
    "Rating": 19.45507560487017,
    "Rank": 13
  },
  {
    "Year": 2016,
    "Method": "massey",
    "Weight": "sigmoid",
    "Conference": "",
    "Team": "Texas A&M",
    "Rating": 19.45453802201898,
    "Rank": 14
  },
  {
    "Year": 2016,
    "Method": "massey",
    "Weight": "sigmoid",
    "Conference": "",
    "Team": "Wichita State",
    "Rating": 19.405566299920157,
    "Rank": 15
  },
  {
    "Year": 2016,
    "Method": "massey",
    "Weight": "sigmoid",
    "Conference": "",
    "Team": "California",
    "Rating": 19.343238214575948,
    "Rank": 16
  },
  {
    "Year": 2016,
    "Method": "massey",
    "Weight": "sigmoid",
    "Conference": "",
    "Team": "Louisville",
    "Rating": 18.98973430775459,
    "Rank": 17
  },
  {
    "Year": 2016,
    "Method": "massey",
    "Weight": "sigmoid",
    "Conference": "",
    "Team": "Miami (FL)",
    "Rating": 18.391771594243743,
    "Rank": 18
  },
  {
    "Year": 2016,
    "Method": "massey",
    "Weight": "sigmoid",
    "Conference": "",
    "Team": "Duke",
    "Rating": 18.083292891544914,
    "Rank": 19
  },
  {
    "Year": 2016,
    "Method": "massey",
    "Weight": "sigmoid",
    "Conference": "",
    "Team": "Xavier",
    "Rating": 17.987745867458543,
    "Rank": 20
  },
  {
    "Year": 2016,
    "Method": "massey",
    "Weight": "sigmoid",
    "Conference": "",
    "Team": "Southern Methodist",
    "Rating": 17.96632876181806,
    "Rank": 21
  },
  {
    "Year": 2016,
    "Method": "massey",
    "Weight": "sigmoid",
    "Conference": "",
    "Team": "Maryland",
    "Rating": 17.67753448175021,
    "Rank": 22
  },
  {
    "Year": 2016,
    "Method": "massey",
    "Weight": "sigmoid",
    "Conference": "",
    "Team": "Baylor",
    "Rating": 17.628441346016466,
    "Rank": 23
  },
  {
    "Year": 2016,
    "Method": "massey",
    "Weight": "sigmoid",
    "Conference": "",
    "Team": "Vanderbilt",
    "Rating": 17.604993424590575,
    "Rank": 24
  },
  {
    "Year": 2016,
    "Method": "massey",
    "Weight": "sigmoid",
    "Conference": "",
    "Team": "Iowa State",
    "Rating": 17.363512838838624,
    "Rank": 25
  },
  {
    "Year": 2016,
    "Method": "massey",
    "Weight": "sigmoid",
    "Conference": "",
    "Team": "Seton Hall",
    "Rating": 16.99549998613409,
    "Rank": 26
  },
  {
    "Year": 2016,
    "Method": "massey",
    "Weight": "sigmoid",
    "Conference": "",
    "Team": "Gonzaga",
    "Rating": 16.69728316252072,
    "Rank": 27
  },
  {
    "Year": 2016,
    "Method": "massey",
    "Weight": "sigmoid",
    "Conference": "",
    "Team": "Connecticut",
    "Rating": 16.223786889442128,
    "Rank": 28
  },
  {
    "Year": 2016,
    "Method": "massey",
    "Weight": "sigmoid",
    "Conference": "",
    "Team": "Iowa",
    "Rating": 16.14430318499822,
    "Rank": 29
  },
  {
    "Year": 2016,
    "Method": "massey",
    "Weight": "sigmoid",
    "Conference": "",
    "Team": "Texas",
    "Rating": 15.944970798860744,
    "Rank": 30
  },
  {
    "Year": 2016,
    "Method": "massey",
    "Weight": "sigmoid",
    "Conference": "",
    "Team": "Wisconsin",
    "Rating": 15.884793679884416,
    "Rank": 31
  },
  {
    "Year": 2016,
    "Method": "massey",
    "Weight": "sigmoid",
    "Conference": "",
    "Team": "Syracuse",
    "Rating": 14.933949787070745,
    "Rank": 32
  },
  {
    "Year": 2016,
    "Method": "massey",
    "Weight": "sigmoid",
    "Conference": "",
    "Team": "Butler",
    "Rating": 14.803665073120063,
    "Rank": 33
  },
  {
    "Year": 2016,
    "Method": "massey",
    "Weight": "sigmoid",
    "Conference": "",
    "Team": "Pittsburgh",
    "Rating": 14.569276356024025,
    "Rank": 34
  },
  {
    "Year": 2016,
    "Method": "massey",
    "Weight": "sigmoid",
    "Conference": "",
    "Team": "Brigham Young",
    "Rating": 14.221264777368962,
    "Rank": 35
  },
  {
    "Year": 2016,
    "Method": "massey",
    "Weight": "sigmoid",
    "Conference": "",
    "Team": "Cincinnati",
    "Rating": 14.120848190353358,
    "Rank": 36
  },
  {
    "Year": 2016,
    "Method": "massey",
    "Weight": "sigmoid",
    "Conference": "",
    "Team": "Clemson",
    "Rating": 14.074984087471568,
    "Rank": 37
  },
  {
    "Year": 2016,
    "Method": "massey",
    "Weight": "sigmoid",
    "Conference": "",
    "Team": "Notre Dame",
    "Rating": 13.98948460192902,
    "Rank": 38
  },
  {
    "Year": 2016,
    "Method": "massey",
    "Weight": "sigmoid",
    "Conference": "",
    "Team": "Florida",
    "Rating": 13.787014344839012,
    "Rank": 39
  },
  {
    "Year": 2016,
    "Method": "massey",
    "Weight": "sigmoid",
    "Conference": "",
    "Team": "Colorado",
    "Rating": 13.75349778999914,
    "Rank": 40
  },
  {
    "Year": 2016,
    "Method": "massey",
    "Weight": "sigmoid",
    "Conference": "",
    "Team": "Southern California",
    "Rating": 13.610421354358609,
    "Rank": 41
  },
  {
    "Year": 2016,
    "Method": "massey",
    "Weight": "sigmoid",
    "Conference": "",
    "Team": "Washington",
    "Rating": 13.564807979927666,
    "Rank": 42
  },
  {
    "Year": 2016,
    "Method": "massey",
    "Weight": "sigmoid",
    "Conference": "",
    "Team": "Virginia Tech",
    "Rating": 13.531176887105213,
    "Rank": 43
  },
  {
    "Year": 2016,
    "Method": "massey",
    "Weight": "sigmoid",
    "Conference": "",
    "Team": "Florida State",
    "Rating": 13.448390569385332,
    "Rank": 44
  },
  {
    "Year": 2016,
    "Method": "massey",
    "Weight": "sigmoid",
    "Conference": "",
    "Team": "Creighton",
    "Rating": 13.440346810583073,
    "Rank": 45
  },
  {
    "Year": 2016,
    "Method": "massey",
    "Weight": "sigmoid",
    "Conference": "",
    "Team": "Virginia Commonwealth",
    "Rating": 13.273260700696891,
    "Rank": 46
  },
  {
    "Year": 2016,
    "Method": "massey",
    "Weight": "sigmoid",
    "Conference": "",
    "Team": "Stephen F. Austin",
    "Rating": 13.158690034869055,
    "Rank": 47
  },
  {
    "Year": 2016,
    "Method": "massey",
    "Weight": "sigmoid",
    "Conference": "",
    "Team": "Texas Tech",
    "Rating": 12.90337399163303,
    "Rank": 48
  },
  {
    "Year": 2016,
    "Method": "massey",
    "Weight": "sigmoid",
    "Conference": "",
    "Team": "South Carolina",
    "Rating": 12.764831061871366,
    "Rank": 49
  },
  {
    "Year": 2016,
    "Method": "massey",
    "Weight": "sigmoid",
    "Conference": "",
    "Team": "Kansas State",
    "Rating": 12.70111368331779,
    "Rank": 50
  },
  {
    "Year": 2016,
    "Method": "massey",
    "Weight": "sigmoid",
    "Conference": "",
    "Team": "Michigan",
    "Rating": 12.698710583661754,
    "Rank": 51
  },
  {
    "Year": 2016,
    "Method": "massey",
    "Weight": "sigmoid",
    "Conference": "",
    "Team": "Houston",
    "Rating": 12.51198823845882,
    "Rank": 52
  },
  {
    "Year": 2016,
    "Method": "massey",
    "Weight": "sigmoid",
    "Conference": "",
    "Team": "San Diego State",
    "Rating": 12.501176462936744,
    "Rank": 53
  },
  {
    "Year": 2016,
    "Method": "massey",
    "Weight": "sigmoid",
    "Conference": "",
    "Team": "Oregon State",
    "Rating": 12.500672080195985,
    "Rank": 54
  },
  {
    "Year": 2016,
    "Method": "massey",
    "Weight": "sigmoid",
    "Conference": "",
    "Team": "Saint Joseph's",
    "Rating": 12.423876456259112,
    "Rank": 55
  },
  {
    "Year": 2016,
    "Method": "massey",
    "Weight": "sigmoid",
    "Conference": "",
    "Team": "Providence",
    "Rating": 12.414075070995835,
    "Rank": 56
  },
  {
    "Year": 2016,
    "Method": "massey",
    "Weight": "sigmoid",
    "Conference": "",
    "Team": "Georgia Tech",
    "Rating": 12.26308885917454,
    "Rank": 57
  },
  {
    "Year": 2016,
    "Method": "massey",
    "Weight": "sigmoid",
    "Conference": "",
    "Team": "Saint Mary's (CA)",
    "Rating": 11.507577403247453,
    "Rank": 58
  },
  {
    "Year": 2016,
    "Method": "massey",
    "Weight": "sigmoid",
    "Conference": "",
    "Team": "Northwestern",
    "Rating": 11.378878984972918,
    "Rank": 59
  },
  {
    "Year": 2016,
    "Method": "massey",
    "Weight": "sigmoid",
    "Conference": "",
    "Team": "UCLA",
    "Rating": 11.349697668124644,
    "Rank": 60
  },
  {
    "Year": 2016,
    "Method": "massey",
    "Weight": "sigmoid",
    "Conference": "",
    "Team": "Mississippi State",
    "Rating": 11.247058861530128,
    "Rank": 61
  },
  {
    "Year": 2016,
    "Method": "massey",
    "Weight": "sigmoid",
    "Conference": "",
    "Team": "Georgia",
    "Rating": 11.202251877039354,
    "Rank": 62
  },
  {
    "Year": 2016,
    "Method": "massey",
    "Weight": "sigmoid",
    "Conference": "",
    "Team": "Yale",
    "Rating": 11.09852610338785,
    "Rank": 63
  },
  {
    "Year": 2016,
    "Method": "massey",
    "Weight": "sigmoid",
    "Conference": "",
    "Team": "Mississippi",
    "Rating": 10.938268467696876,
    "Rank": 64
  },
  {
    "Year": 2016,
    "Method": "massey",
    "Weight": "sigmoid",
    "Conference": "",
    "Team": "Ohio State",
    "Rating": 10.76176117158765,
    "Rank": 65
  },
  {
    "Year": 2016,
    "Method": "massey",
    "Weight": "sigmoid",
    "Conference": "",
    "Team": "Tulsa",
    "Rating": 10.52682764014937,
    "Rank": 66
  },
  {
    "Year": 2016,
    "Method": "massey",
    "Weight": "sigmoid",
    "Conference": "",
    "Team": "NC State",
    "Rating": 10.510142700989183,
    "Rank": 67
  },
  {
    "Year": 2016,
    "Method": "massey",
    "Weight": "sigmoid",
    "Conference": "",
    "Team": "Memphis",
    "Rating": 10.439085364440787,
    "Rank": 68
  },
  {
    "Year": 2016,
    "Method": "massey",
    "Weight": "sigmoid",
    "Conference": "",
    "Team": "Arkansas",
    "Rating": 10.332495421187636,
    "Rank": 69
  },
  {
    "Year": 2016,
    "Method": "massey",
    "Weight": "sigmoid",
    "Conference": "",
    "Team": "Nebraska",
    "Rating": 10.30036288037811,
    "Rank": 70
  },
  {
    "Year": 2016,
    "Method": "massey",
    "Weight": "sigmoid",
    "Conference": "",
    "Team": "Dayton",
    "Rating": 10.252574652951012,
    "Rank": 71
  },
  {
    "Year": 2016,
    "Method": "massey",
    "Weight": "sigmoid",
    "Conference": "",
    "Team": "Georgetown",
    "Rating": 10.245768311915764,
    "Rank": 72
  },
  {
    "Year": 2016,
    "Method": "massey",
    "Weight": "sigmoid",
    "Conference": "",
    "Team": "Northern Iowa",
    "Rating": 9.967595016413624,
    "Rank": 73
  },
  {
    "Year": 2016,
    "Method": "massey",
    "Weight": "sigmoid",
    "Conference": "",
    "Team": "Valparaiso",
    "Rating": 9.690063164407931,
    "Rank": 74
  },
  {
    "Year": 2016,
    "Method": "massey",
    "Weight": "sigmoid",
    "Conference": "",
    "Team": "George Washington",
    "Rating": 9.230115665789278,
    "Rank": 75
  },
  {
    "Year": 2016,
    "Method": "massey",
    "Weight": "sigmoid",
    "Conference": "",
    "Team": "Alabama",
    "Rating": 9.169267877877164,
    "Rank": 76
  },
  {
    "Year": 2016,
    "Method": "massey",
    "Weight": "sigmoid",
    "Conference": "",
    "Team": "Louisiana State",
    "Rating": 9.15157488303888,
    "Rank": 77
  },
  {
    "Year": 2016,
    "Method": "massey",
    "Weight": "sigmoid",
    "Conference": "",
    "Team": "Temple",
    "Rating": 8.740920549739279,
    "Rank": 78
  },
  {
    "Year": 2016,
    "Method": "massey",
    "Weight": "sigmoid",
    "Conference": "",
    "Team": "Princeton",
    "Rating": 8.631676130509792,
    "Rank": 79
  },
  {
    "Year": 2016,
    "Method": "massey",
    "Weight": "sigmoid",
    "Conference": "",
    "Team": "Evansville",
    "Rating": 8.556045393236058,
    "Rank": 80
  },
  {
    "Year": 2016,
    "Method": "massey",
    "Weight": "sigmoid",
    "Conference": "",
    "Team": "Hawaii",
    "Rating": 8.242601843913258,
    "Rank": 81
  },
  {
    "Year": 2016,
    "Method": "massey",
    "Weight": "sigmoid",
    "Conference": "",
    "Team": "Tennessee",
    "Rating": 8.102847570775547,
    "Rank": 82
  },
  {
    "Year": 2016,
    "Method": "massey",
    "Weight": "sigmoid",
    "Conference": "",
    "Team": "Oklahoma State",
    "Rating": 8.087785199093535,
    "Rank": 83
  },
  {
    "Year": 2016,
    "Method": "massey",
    "Weight": "sigmoid",
    "Conference": "",
    "Team": "Stanford",
    "Rating": 8.067259593677004,
    "Rank": 84
  },
  {
    "Year": 2016,
    "Method": "massey",
    "Weight": "sigmoid",
    "Conference": "",
    "Team": "St. Bonaventure",
    "Rating": 7.664710810243752,
    "Rank": 85
  },
  {
    "Year": 2016,
    "Method": "massey",
    "Weight": "sigmoid",
    "Conference": "",
    "Team": "Marquette",
    "Rating": 7.618066659936911,
    "Rank": 86
  },
  {
    "Year": 2016,
    "Method": "massey",
    "Weight": "sigmoid",
    "Conference": "",
    "Team": "Arizona State",
    "Rating": 7.412589144017675,
    "Rank": 87
  },
  {
    "Year": 2016,
    "Method": "massey",
    "Weight": "sigmoid",
    "Conference": "",
    "Team": "Little Rock",
    "Rating": 7.309616479418109,
    "Rank": 88
  },
  {
    "Year": 2016,
    "Method": "massey",
    "Weight": "sigmoid",
    "Conference": "",
    "Team": "Fresno State",
    "Rating": 6.914993289923176,
    "Rank": 89
  },
  {
    "Year": 2016,
    "Method": "massey",
    "Weight": "sigmoid",
    "Conference": "",
    "Team": "Illinois State",
    "Rating": 6.817006835924307,
    "Rank": 90
  },
  {
    "Year": 2016,
    "Method": "massey",
    "Weight": "sigmoid",
    "Conference": "",
    "Team": "Oakland",
    "Rating": 6.723086765554278,
    "Rank": 91
  },
  {
    "Year": 2016,
    "Method": "massey",
    "Weight": "sigmoid",
    "Conference": "",
    "Team": "UC Santa Barbara",
    "Rating": 6.505929074396629,
    "Rank": 92
  },
  {
    "Year": 2016,
    "Method": "massey",
    "Weight": "sigmoid",
    "Conference": "",
    "Team": "UNC Wilmington",
    "Rating": 6.50194164046963,
    "Rank": 93
  },
  {
    "Year": 2016,
    "Method": "massey",
    "Weight": "sigmoid",
    "Conference": "",
    "Team": "Wake Forest",
    "Rating": 6.496523049491238,
    "Rank": 94
  },
  {
    "Year": 2016,
    "Method": "massey",
    "Weight": "sigmoid",
    "Conference": "",
    "Team": "Boise State",
    "Rating": 6.476700311500828,
    "Rank": 95
  },
  {
    "Year": 2016,
    "Method": "massey",
    "Weight": "sigmoid",
    "Conference": "",
    "Team": "Rhode Island",
    "Rating": 6.292220550486224,
    "Rank": 96
  },
  {
    "Year": 2016,
    "Method": "massey",
    "Weight": "sigmoid",
    "Conference": "",
    "Team": "Hofstra",
    "Rating": 6.25167935408205,
    "Rank": 97
  },
  {
    "Year": 2016,
    "Method": "massey",
    "Weight": "sigmoid",
    "Conference": "",
    "Team": "James Madison",
    "Rating": 6.225409573770838,
    "Rank": 98
  },
  {
    "Year": 2016,
    "Method": "massey",
    "Weight": "sigmoid",
    "Conference": "",
    "Team": "William & Mary",
    "Rating": 6.036406375463208,
    "Rank": 99
  },
  {
    "Year": 2016,
    "Method": "massey",
    "Weight": "sigmoid",
    "Conference": "",
    "Team": "Iona",
    "Rating": 6.0148657722190215,
    "Rank": 100
  },
  {
    "Year": 2016,
    "Method": "massey",
    "Weight": "sigmoid",
    "Conference": "",
    "Team": "Monmouth",
    "Rating": 5.86118238415345,
    "Rank": 101
  },
  {
    "Year": 2016,
    "Method": "massey",
    "Weight": "sigmoid",
    "Conference": "",
    "Team": "Akron",
    "Rating": 5.839088838109678,
    "Rank": 102
  },
  {
    "Year": 2016,
    "Method": "massey",
    "Weight": "sigmoid",
    "Conference": "",
    "Team": "Illinois",
    "Rating": 5.77562919264042,
    "Rank": 103
  },
  {
    "Year": 2016,
    "Method": "massey",
    "Weight": "sigmoid",
    "Conference": "",
    "Team": "Davidson",
    "Rating": 5.610680565856709,
    "Rank": 104
  },
  {
    "Year": 2016,
    "Method": "massey",
    "Weight": "sigmoid",
    "Conference": "",
    "Team": "Penn State",
    "Rating": 5.604558717294236,
    "Rank": 105
  },
  {
    "Year": 2016,
    "Method": "massey",
    "Weight": "sigmoid",
    "Conference": "",
    "Team": "UC Irvine",
    "Rating": 5.278815848073522,
    "Rank": 106
  },
  {
    "Year": 2016,
    "Method": "massey",
    "Weight": "sigmoid",
    "Conference": "",
    "Team": "Richmond",
    "Rating": 4.816418957172253,
    "Rank": 107
  },
  {
    "Year": 2016,
    "Method": "massey",
    "Weight": "sigmoid",
    "Conference": "",
    "Team": "TCU",
    "Rating": 4.697789433572417,
    "Rank": 108
  },
  {
    "Year": 2016,
    "Method": "massey",
    "Weight": "sigmoid",
    "Conference": "",
    "Team": "Milwaukee",
    "Rating": 4.553748741263817,
    "Rank": 109
  },
  {
    "Year": 2016,
    "Method": "massey",
    "Weight": "sigmoid",
    "Conference": "",
    "Team": "Cal State Bakersfield",
    "Rating": 4.490886404811171,
    "Rank": 110
  },
  {
    "Year": 2016,
    "Method": "massey",
    "Weight": "sigmoid",
    "Conference": "",
    "Team": "UT Arlington",
    "Rating": 4.380169531107202,
    "Rank": 111
  },
  {
    "Year": 2016,
    "Method": "massey",
    "Weight": "sigmoid",
    "Conference": "",
    "Team": "New Mexico State",
    "Rating": 4.08220978558068,
    "Rank": 112
  },
  {
    "Year": 2016,
    "Method": "massey",
    "Weight": "sigmoid",
    "Conference": "",
    "Team": "Utah State",
    "Rating": 4.077221719340251,
    "Rank": 113
  },
  {
    "Year": 2016,
    "Method": "massey",
    "Weight": "sigmoid",
    "Conference": "",
    "Team": "Old Dominion",
    "Rating": 4.025018405979704,
    "Rank": 114
  },
  {
    "Year": 2016,
    "Method": "massey",
    "Weight": "sigmoid",
    "Conference": "",
    "Team": "Missouri",
    "Rating": 3.8606055626430393,
    "Rank": 115
  },
  {
    "Year": 2016,
    "Method": "massey",
    "Weight": "sigmoid",
    "Conference": "",
    "Team": "UAB",
    "Rating": 3.797745208327413,
    "Rank": 116
  },
  {
    "Year": 2016,
    "Method": "massey",
    "Weight": "sigmoid",
    "Conference": "",
    "Team": "Columbia",
    "Rating": 3.722593305977027,
    "Rank": 117
  },
  {
    "Year": 2016,
    "Method": "massey",
    "Weight": "sigmoid",
    "Conference": "",
    "Team": "South Dakota State",
    "Rating": 3.7216806024242826,
    "Rank": 118
  },
  {
    "Year": 2016,
    "Method": "massey",
    "Weight": "sigmoid",
    "Conference": "",
    "Team": "Green Bay",
    "Rating": 3.679658008822401,
    "Rank": 119
  },
  {
    "Year": 2016,
    "Method": "massey",
    "Weight": "sigmoid",
    "Conference": "",
    "Team": "Stony Brook",
    "Rating": 3.6405487800308247,
    "Rank": 120
  },
  {
    "Year": 2016,
    "Method": "massey",
    "Weight": "sigmoid",
    "Conference": "",
    "Team": "Long Beach State",
    "Rating": 3.452778520183018,
    "Rank": 121
  },
  {
    "Year": 2016,
    "Method": "massey",
    "Weight": "sigmoid",
    "Conference": "",
    "Team": "Middle Tennessee",
    "Rating": 3.0975454529461786,
    "Rank": 122
  },
  {
    "Year": 2016,
    "Method": "massey",
    "Weight": "sigmoid",
    "Conference": "",
    "Team": "Siena",
    "Rating": 3.0035986404971826,
    "Rank": 123
  },
  {
    "Year": 2016,
    "Method": "massey",
    "Weight": "sigmoid",
    "Conference": "",
    "Team": "Louisiana",
    "Rating": 2.9378157805787914,
    "Rank": 124
  },
  {
    "Year": 2016,
    "Method": "massey",
    "Weight": "sigmoid",
    "Conference": "",
    "Team": "Pepperdine",
    "Rating": 2.9369977087164805,
    "Rank": 125
  },
  {
    "Year": 2016,
    "Method": "massey",
    "Weight": "sigmoid",
    "Conference": "",
    "Team": "Toledo",
    "Rating": 2.763533116406517,
    "Rank": 126
  },
  {
    "Year": 2016,
    "Method": "massey",
    "Weight": "sigmoid",
    "Conference": "",
    "Team": "UNC Asheville",
    "Rating": 2.7615787552584248,
    "Rank": 127
  },
  {
    "Year": 2016,
    "Method": "massey",
    "Weight": "sigmoid",
    "Conference": "",
    "Team": "Wright State",
    "Rating": 2.6694118199650063,
    "Rank": 128
  },
  {
    "Year": 2016,
    "Method": "massey",
    "Weight": "sigmoid",
    "Conference": "",
    "Team": "Louisiana-Monroe",
    "Rating": 2.6674188075078566,
    "Rank": 129
  },
  {
    "Year": 2016,
    "Method": "massey",
    "Weight": "sigmoid",
    "Conference": "",
    "Team": "Chattanooga",
    "Rating": 2.6284905151907907,
    "Rank": 130
  },
  {
    "Year": 2016,
    "Method": "massey",
    "Weight": "sigmoid",
    "Conference": "",
    "Team": "Colorado State",
    "Rating": 2.603630956624752,
    "Rank": 131
  },
  {
    "Year": 2016,
    "Method": "massey",
    "Weight": "sigmoid",
    "Conference": "",
    "Team": "Purdue Fort Wayne",
    "Rating": 2.549956063342675,
    "Rank": 132
  },
  {
    "Year": 2016,
    "Method": "massey",
    "Weight": "sigmoid",
    "Conference": "",
    "Team": "Buffalo",
    "Rating": 2.5393917912672883,
    "Rank": 133
  },
  {
    "Year": 2016,
    "Method": "massey",
    "Weight": "sigmoid",
    "Conference": "",
    "Team": "Southern Illinois",
    "Rating": 2.412140345787008,
    "Rank": 134
  },
  {
    "Year": 2016,
    "Method": "massey",
    "Weight": "sigmoid",
    "Conference": "",
    "Team": "New Mexico",
    "Rating": 2.365689609069795,
    "Rank": 135
  },
  {
    "Year": 2016,
    "Method": "massey",
    "Weight": "sigmoid",
    "Conference": "",
    "Team": "Towson",
    "Rating": 2.2773939960047445,
    "Rank": 136
  },
  {
    "Year": 2016,
    "Method": "massey",
    "Weight": "sigmoid",
    "Conference": "",
    "Team": "College of Charleston",
    "Rating": 2.180934503022213,
    "Rank": 137
  },
  {
    "Year": 2016,
    "Method": "massey",
    "Weight": "sigmoid",
    "Conference": "",
    "Team": "Nevada",
    "Rating": 2.1510915763049727,
    "Rank": 138
  },
  {
    "Year": 2016,
    "Method": "massey",
    "Weight": "sigmoid",
    "Conference": "",
    "Team": "Northeastern",
    "Rating": 2.112052377170374,
    "Rank": 139
  },
  {
    "Year": 2016,
    "Method": "massey",
    "Weight": "sigmoid",
    "Conference": "",
    "Team": "Nevada-Las Vegas",
    "Rating": 2.094195048372886,
    "Rank": 140
  },
  {
    "Year": 2016,
    "Method": "massey",
    "Weight": "sigmoid",
    "Conference": "",
    "Team": "Marshall",
    "Rating": 2.0637047926100536,
    "Rank": 141
  },
  {
    "Year": 2016,
    "Method": "massey",
    "Weight": "sigmoid",
    "Conference": "",
    "Team": "Albany (NY)",
    "Rating": 2.041621086174894,
    "Rank": 142
  },
  {
    "Year": 2016,
    "Method": "massey",
    "Weight": "sigmoid",
    "Conference": "",
    "Team": "Ohio",
    "Rating": 1.962502686094174,
    "Rank": 143
  },
  {
    "Year": 2016,
    "Method": "massey",
    "Weight": "sigmoid",
    "Conference": "",
    "Team": "Loyola (IL)",
    "Rating": 1.890832197478021,
    "Rank": 144
  },
  {
    "Year": 2016,
    "Method": "massey",
    "Weight": "sigmoid",
    "Conference": "",
    "Team": "Winthrop",
    "Rating": 1.097788323633175,
    "Rank": 145
  },
  {
    "Year": 2016,
    "Method": "massey",
    "Weight": "sigmoid",
    "Conference": "",
    "Team": "Central Michigan",
    "Rating": 1.038770588453655,
    "Rank": 146
  },
  {
    "Year": 2016,
    "Method": "massey",
    "Weight": "sigmoid",
    "Conference": "",
    "Team": "Ball State",
    "Rating": 0.9800604818729112,
    "Rank": 147
  },
  {
    "Year": 2016,
    "Method": "massey",
    "Weight": "sigmoid",
    "Conference": "",
    "Team": "Vermont",
    "Rating": 0.5927150326023285,
    "Rank": 148
  },
  {
    "Year": 2016,
    "Method": "massey",
    "Weight": "sigmoid",
    "Conference": "",
    "Team": "Fordham",
    "Rating": 0.4721935127749555,
    "Rank": 149
  },
  {
    "Year": 2016,
    "Method": "massey",
    "Weight": "sigmoid",
    "Conference": "",
    "Team": "Massachusetts",
    "Rating": 0.429332600734928,
    "Rank": 150
  },
  {
    "Year": 2016,
    "Method": "massey",
    "Weight": "sigmoid",
    "Conference": "",
    "Team": "Montana",
    "Rating": 0.3690051033722632,
    "Rank": 151
  },
  {
    "Year": 2016,
    "Method": "massey",
    "Weight": "sigmoid",
    "Conference": "",
    "Team": "Duquesne",
    "Rating": 0.2809042218959252,
    "Rank": 152
  },
  {
    "Year": 2016,
    "Method": "massey",
    "Weight": "sigmoid",
    "Conference": "",
    "Team": "Western Kentucky",
    "Rating": 0.1080749561477247,
    "Rank": 153
  },
  {
    "Year": 2016,
    "Method": "massey",
    "Weight": "sigmoid",
    "Conference": "",
    "Team": "Murray State",
    "Rating": 0.0506558307561526,
    "Rank": 154
  },
  {
    "Year": 2016,
    "Method": "massey",
    "Weight": "sigmoid",
    "Conference": "",
    "Team": "SIU Edwardsville",
    "Rating": 5.3458620671704713e-14,
    "Rank": 155
  },
  {
    "Year": 2016,
    "Method": "massey",
    "Weight": "sigmoid",
    "Conference": "",
    "Team": "IU Indy",
    "Rating": -4.0169178489464725e-14,
    "Rank": 156
  },
  {
    "Year": 2016,
    "Method": "massey",
    "Weight": "sigmoid",
    "Conference": "",
    "Team": "Wyoming",
    "Rating": -0.031927979468286,
    "Rank": 157
  },
  {
    "Year": 2016,
    "Method": "massey",
    "Weight": "sigmoid",
    "Conference": "",
    "Team": "Morehead State",
    "Rating": -0.0818734411573105,
    "Rank": 158
  },
  {
    "Year": 2016,
    "Method": "massey",
    "Weight": "sigmoid",
    "Conference": "",
    "Team": "Eastern Michigan",
    "Rating": -0.1258551024384786,
    "Rank": 159
  },
  {
    "Year": 2016,
    "Method": "massey",
    "Weight": "sigmoid",
    "Conference": "",
    "Team": "Elon",
    "Rating": -0.168338726101985,
    "Rank": 160
  },
  {
    "Year": 2016,
    "Method": "massey",
    "Weight": "sigmoid",
    "Conference": "",
    "Team": "Minnesota",
    "Rating": -0.2523104765327204,
    "Rank": 161
  },
  {
    "Year": 2016,
    "Method": "massey",
    "Weight": "sigmoid",
    "Conference": "",
    "Team": "Central Florida",
    "Rating": -0.330798801809979,
    "Rank": 162
  },
  {
    "Year": 2016,
    "Method": "massey",
    "Weight": "sigmoid",
    "Conference": "",
    "Team": "Tulane",
    "Rating": -0.3566146489123838,
    "Rank": 163
  },
  {
    "Year": 2016,
    "Method": "massey",
    "Weight": "sigmoid",
    "Conference": "",
    "Team": "East Tennessee State",
    "Rating": -0.3624253972889093,
    "Rank": 164
  },
  {
    "Year": 2016,
    "Method": "massey",
    "Weight": "sigmoid",
    "Conference": "",
    "Team": "Belmont",
    "Rating": -0.4582174253634843,
    "Rank": 165
  },
  {
    "Year": 2016,
    "Method": "massey",
    "Weight": "sigmoid",
    "Conference": "",
    "Team": "Louisiana Tech",
    "Rating": -0.4605600814440365,
    "Rank": 166
  },
  {
    "Year": 2016,
    "Method": "massey",
    "Weight": "sigmoid",
    "Conference": "",
    "Team": "Grand Canyon",
    "Rating": -0.5382553110182791,
    "Rank": 167
  },
  {
    "Year": 2016,
    "Method": "massey",
    "Weight": "sigmoid",
    "Conference": "",
    "Team": "Omaha",
    "Rating": -0.5480967477898453,
    "Rank": 168
  },
  {
    "Year": 2016,
    "Method": "massey",
    "Weight": "sigmoid",
    "Conference": "",
    "Team": "Charlotte",
    "Rating": -0.6032290742699775,
    "Rank": 169
  },
  {
    "Year": 2016,
    "Method": "massey",
    "Weight": "sigmoid",
    "Conference": "",
    "Team": "Tennessee State",
    "Rating": -0.6806246339731885,
    "Rank": 170
  },
  {
    "Year": 2016,
    "Method": "massey",
    "Weight": "sigmoid",
    "Conference": "",
    "Team": "DePaul",
    "Rating": -0.6851030519061814,
    "Rank": 171
  },
  {
    "Year": 2016,
    "Method": "massey",
    "Weight": "sigmoid",
    "Conference": "",
    "Team": "Coastal Carolina",
    "Rating": -0.7388580851788912,
    "Rank": 172
  },
  {
    "Year": 2016,
    "Method": "massey",
    "Weight": "sigmoid",
    "Conference": "",
    "Team": "Boston College",
    "Rating": -0.8060130240701202,
    "Rank": 173
  },
  {
    "Year": 2016,
    "Method": "massey",
    "Weight": "sigmoid",
    "Conference": "",
    "Team": "Washington State",
    "Rating": -0.8196083340392342,
    "Rank": 174
  },
  {
    "Year": 2016,
    "Method": "massey",
    "Weight": "sigmoid",
    "Conference": "",
    "Team": "High Point",
    "Rating": -0.8669347535287635,
    "Rank": 175
  },
  {
    "Year": 2016,
    "Method": "massey",
    "Weight": "sigmoid",
    "Conference": "",
    "Team": "Weber State",
    "Rating": -1.0063298089932635,
    "Rank": 176
  },
  {
    "Year": 2016,
    "Method": "massey",
    "Weight": "sigmoid",
    "Conference": "",
    "Team": "Northern Illinois",
    "Rating": -1.0321970645785523,
    "Rank": 177
  },
  {
    "Year": 2016,
    "Method": "massey",
    "Weight": "sigmoid",
    "Conference": "",
    "Team": "Detroit Mercy",
    "Rating": -1.0369757876452326,
    "Rank": 178
  },
  {
    "Year": 2016,
    "Method": "massey",
    "Weight": "sigmoid",
    "Conference": "",
    "Team": "East Carolina",
    "Rating": -1.1677162577741689,
    "Rank": 179
  },
  {
    "Year": 2016,
    "Method": "massey",
    "Weight": "sigmoid",
    "Conference": "",
    "Team": "Indiana State",
    "Rating": -1.218715210955736,
    "Rank": 180
  },
  {
    "Year": 2016,
    "Method": "massey",
    "Weight": "sigmoid",
    "Conference": "",
    "Team": "Harvard",
    "Rating": -1.219258117680249,
    "Rank": 181
  },
  {
    "Year": 2016,
    "Method": "massey",
    "Weight": "sigmoid",
    "Conference": "",
    "Team": "Bucknell",
    "Rating": -1.35319782854565,
    "Rank": 182
  },
  {
    "Year": 2016,
    "Method": "massey",
    "Weight": "sigmoid",
    "Conference": "",
    "Team": "Lehigh",
    "Rating": -1.3865902174384903,
    "Rank": 183
  },
  {
    "Year": 2016,
    "Method": "massey",
    "Weight": "sigmoid",
    "Conference": "",
    "Team": "South Florida",
    "Rating": -1.479049971899042,
    "Rank": 184
  },
  {
    "Year": 2016,
    "Method": "massey",
    "Weight": "sigmoid",
    "Conference": "",
    "Team": "Auburn",
    "Rating": -1.5829554248658866,
    "Rank": 185
  },
  {
    "Year": 2016,
    "Method": "massey",
    "Weight": "sigmoid",
    "Conference": "",
    "Team": "Furman",
    "Rating": -1.7441818592615137,
    "Rank": 186
  },
  {
    "Year": 2016,
    "Method": "massey",
    "Weight": "sigmoid",
    "Conference": "",
    "Team": "Florida Gulf Coast",
    "Rating": -1.75856647516691,
    "Rank": 187
  },
  {
    "Year": 2016,
    "Method": "massey",
    "Weight": "sigmoid",
    "Conference": "",
    "Team": "St. John's (NY)",
    "Rating": -1.8475281382008892,
    "Rank": 188
  },
  {
    "Year": 2016,
    "Method": "massey",
    "Weight": "sigmoid",
    "Conference": "",
    "Team": "San Francisco",
    "Rating": -2.005137184292205,
    "Rank": 189
  },
  {
    "Year": 2016,
    "Method": "massey",
    "Weight": "sigmoid",
    "Conference": "",
    "Team": "Denver",
    "Rating": -2.010043904127245,
    "Rank": 190
  },
  {
    "Year": 2016,
    "Method": "massey",
    "Weight": "sigmoid",
    "Conference": "",
    "Team": "Pacific",
    "Rating": -2.0334769644999,
    "Rank": 191
  },
  {
    "Year": 2016,
    "Method": "massey",
    "Weight": "sigmoid",
    "Conference": "",
    "Team": "North Dakota State",
    "Rating": -2.0354102201901307,
    "Rank": 192
  },
  {
    "Year": 2016,
    "Method": "massey",
    "Weight": "sigmoid",
    "Conference": "",
    "Team": "Georgia Southern",
    "Rating": -2.046549378479701,
    "Rank": 193
  },
  {
    "Year": 2016,
    "Method": "massey",
    "Weight": "sigmoid",
    "Conference": "",
    "Team": "Wagner",
    "Rating": -2.137168209633408,
    "Rank": 194
  },
  {
    "Year": 2016,
    "Method": "massey",
    "Weight": "sigmoid",
    "Conference": "",
    "Team": "Western Michigan",
    "Rating": -2.143574004769283,
    "Rank": 195
  },
  {
    "Year": 2016,
    "Method": "massey",
    "Weight": "sigmoid",
    "Conference": "",
    "Team": "Portland",
    "Rating": -2.1988888458985345,
    "Rank": 196
  },
  {
    "Year": 2016,
    "Method": "massey",
    "Weight": "sigmoid",
    "Conference": "",
    "Team": "Loyola Marymount",
    "Rating": -2.2627615648878234,
    "Rank": 197
  },
  {
    "Year": 2016,
    "Method": "massey",
    "Weight": "sigmoid",
    "Conference": "",
    "Team": "George Mason",
    "Rating": -2.4472910968199404,
    "Rank": 198
  },
  {
    "Year": 2016,
    "Method": "massey",
    "Weight": "sigmoid",
    "Conference": "",
    "Team": "North Dakota",
    "Rating": -2.51195307127115,
    "Rank": 199
  },
  {
    "Year": 2016,
    "Method": "massey",
    "Weight": "sigmoid",
    "Conference": "",
    "Team": "Wofford",
    "Rating": -2.5615349252654083,
    "Rank": 200
  },
  {
    "Year": 2016,
    "Method": "massey",
    "Weight": "sigmoid",
    "Conference": "",
    "Team": "Fairfield",
    "Rating": -2.5868798267523445,
    "Rank": 201
  },
  {
    "Year": 2016,
    "Method": "massey",
    "Weight": "sigmoid",
    "Conference": "",
    "Team": "Texas A&M-Corpus Christi",
    "Rating": -2.629301581540856,
    "Rank": 202
  },
  {
    "Year": 2016,
    "Method": "massey",
    "Weight": "sigmoid",
    "Conference": "",
    "Team": "Kent State",
    "Rating": -2.714447748647517,
    "Rank": 203
  },
  {
    "Year": 2016,
    "Method": "massey",
    "Weight": "sigmoid",
    "Conference": "",
    "Team": "Missouri State",
    "Rating": -2.9838819789411275,
    "Rank": 204
  },
  {
    "Year": 2016,
    "Method": "massey",
    "Weight": "sigmoid",
    "Conference": "",
    "Team": "Eastern Kentucky",
    "Rating": -3.1112499929412074,
    "Rank": 205
  },
  {
    "Year": 2016,
    "Method": "massey",
    "Weight": "sigmoid",
    "Conference": "",
    "Team": "Saint Louis",
    "Rating": -3.196403259273522,
    "Rank": 206
  },
  {
    "Year": 2016,
    "Method": "massey",
    "Weight": "sigmoid",
    "Conference": "",
    "Team": "Tennessee-Martin",
    "Rating": -3.2820585259986963,
    "Rank": 207
  },
  {
    "Year": 2016,
    "Method": "massey",
    "Weight": "sigmoid",
    "Conference": "",
    "Team": "Texas State",
    "Rating": -3.441921094246986,
    "Rank": 208
  },
  {
    "Year": 2016,
    "Method": "massey",
    "Weight": "sigmoid",
    "Conference": "",
    "Team": "Saint Peter's",
    "Rating": -3.5449413101678893,
    "Rank": 209
  },
  {
    "Year": 2016,
    "Method": "massey",
    "Weight": "sigmoid",
    "Conference": "",
    "Team": "North Florida",
    "Rating": -3.642650790416732,
    "Rank": 210
  },
  {
    "Year": 2016,
    "Method": "massey",
    "Weight": "sigmoid",
    "Conference": "",
    "Team": "Austin Peay",
    "Rating": -3.647000811627757,
    "Rank": 211
  },
  {
    "Year": 2016,
    "Method": "massey",
    "Weight": "sigmoid",
    "Conference": "",
    "Team": "Georgia State",
    "Rating": -3.7237824285405,
    "Rank": 212
  },
  {
    "Year": 2016,
    "Method": "massey",
    "Weight": "sigmoid",
    "Conference": "",
    "Team": "UTEP",
    "Rating": -3.726674882699751,
    "Rank": 213
  },
  {
    "Year": 2016,
    "Method": "massey",
    "Weight": "sigmoid",
    "Conference": "",
    "Team": "Dartmouth",
    "Rating": -3.7669491889780193,
    "Rank": 214
  },
  {
    "Year": 2016,
    "Method": "massey",
    "Weight": "sigmoid",
    "Conference": "",
    "Team": "UNC Greensboro",
    "Rating": -3.847223632086152,
    "Rank": 215
  },
  {
    "Year": 2016,
    "Method": "massey",
    "Weight": "sigmoid",
    "Conference": "",
    "Team": "Eastern Washington",
    "Rating": -3.86840799115431,
    "Rank": 216
  },
  {
    "Year": 2016,
    "Method": "massey",
    "Weight": "sigmoid",
    "Conference": "",
    "Team": "Western Carolina",
    "Rating": -3.9253180621849424,
    "Rank": 217
  },
  {
    "Year": 2016,
    "Method": "massey",
    "Weight": "sigmoid",
    "Conference": "",
    "Team": "Texas Southern",
    "Rating": -4.146814973102657,
    "Rank": 218
  },
  {
    "Year": 2016,
    "Method": "massey",
    "Weight": "sigmoid",
    "Conference": "",
    "Team": "Santa Clara",
    "Rating": -4.163755699110936,
    "Rank": 219
  },
  {
    "Year": 2016,
    "Method": "massey",
    "Weight": "sigmoid",
    "Conference": "",
    "Team": "San Jose State",
    "Rating": -4.197788694821576,
    "Rank": 220
  },
  {
    "Year": 2016,
    "Method": "massey",
    "Weight": "sigmoid",
    "Conference": "",
    "Team": "Idaho",
    "Rating": -4.269295405874143,
    "Rank": 221
  },
  {
    "Year": 2016,
    "Method": "massey",
    "Weight": "sigmoid",
    "Conference": "",
    "Team": "Rider",
    "Rating": -4.362050857864524,
    "Rank": 222
  },
  {
    "Year": 2016,
    "Method": "massey",
    "Weight": "sigmoid",
    "Conference": "",
    "Team": "Tennessee Tech",
    "Rating": -4.380482143344725,
    "Rank": 223
  },
  {
    "Year": 2016,
    "Method": "massey",
    "Weight": "sigmoid",
    "Conference": "",
    "Team": "Oral Roberts",
    "Rating": -4.570269602216165,
    "Rank": 224
  },
  {
    "Year": 2016,
    "Method": "massey",
    "Weight": "sigmoid",
    "Conference": "",
    "Team": "Sam Houston",
    "Rating": -4.603638889509906,
    "Rank": 225
  },
  {
    "Year": 2016,
    "Method": "massey",
    "Weight": "sigmoid",
    "Conference": "",
    "Team": "UC Davis",
    "Rating": -4.643922307434902,
    "Rank": 226
  },
  {
    "Year": 2016,
    "Method": "massey",
    "Weight": "sigmoid",
    "Conference": "",
    "Team": "Cal State Northridge",
    "Rating": -4.687948282539127,
    "Rank": 227
  },
  {
    "Year": 2016,
    "Method": "massey",
    "Weight": "sigmoid",
    "Conference": "",
    "Team": "Drexel",
    "Rating": -4.784464097387386,
    "Rank": 228
  },
  {
    "Year": 2016,
    "Method": "massey",
    "Weight": "sigmoid",
    "Conference": "",
    "Team": "Pennsylvania",
    "Rating": -5.002181395228036,
    "Rank": 229
  },
  {
    "Year": 2016,
    "Method": "massey",
    "Weight": "sigmoid",
    "Conference": "",
    "Team": "Drake",
    "Rating": -5.034170551610963,
    "Rank": 230
  },
  {
    "Year": 2016,
    "Method": "massey",
    "Weight": "sigmoid",
    "Conference": "",
    "Team": "Air Force",
    "Rating": -5.043551664393871,
    "Rank": 231
  },
  {
    "Year": 2016,
    "Method": "massey",
    "Weight": "sigmoid",
    "Conference": "",
    "Team": "UC Riverside",
    "Rating": -5.303725702731413,
    "Rank": 232
  },
  {
    "Year": 2016,
    "Method": "massey",
    "Weight": "sigmoid",
    "Conference": "",
    "Team": "Florida International",
    "Rating": -5.312664148634926,
    "Rank": 233
  },
  {
    "Year": 2016,
    "Method": "massey",
    "Weight": "sigmoid",
    "Conference": "",
    "Team": "Cal Poly",
    "Rating": -5.364024340679055,
    "Rank": 234
  },
  {
    "Year": 2016,
    "Method": "massey",
    "Weight": "sigmoid",
    "Conference": "",
    "Team": "Manhattan",
    "Rating": -5.382077863283795,
    "Rank": 235
  },
  {
    "Year": 2016,
    "Method": "massey",
    "Weight": "sigmoid",
    "Conference": "",
    "Team": "Miami (OH)",
    "Rating": -5.486458540871169,
    "Rank": 236
  },
  {
    "Year": 2016,
    "Method": "massey",
    "Weight": "sigmoid",
    "Conference": "",
    "Team": "La Salle",
    "Rating": -5.705951661492219,
    "Rank": 237
  },
  {
    "Year": 2016,
    "Method": "massey",
    "Weight": "sigmoid",
    "Conference": "",
    "Team": "Mercer",
    "Rating": -5.738468059554798,
    "Rank": 238
  },
  {
    "Year": 2016,
    "Method": "massey",
    "Weight": "sigmoid",
    "Conference": "",
    "Team": "Navy",
    "Rating": -5.828063060455312,
    "Rank": 239
  },
  {
    "Year": 2016,
    "Method": "massey",
    "Weight": "sigmoid",
    "Conference": "",
    "Team": "Gardner-Webb",
    "Rating": -5.895380016996046,
    "Rank": 240
  },
  {
    "Year": 2016,
    "Method": "massey",
    "Weight": "sigmoid",
    "Conference": "",
    "Team": "New Hampshire",
    "Rating": -5.935291898461188,
    "Rank": 241
  },
  {
    "Year": 2016,
    "Method": "massey",
    "Weight": "sigmoid",
    "Conference": "",
    "Team": "Norfolk State",
    "Rating": -6.035352891475073,
    "Rank": 242
  },
  {
    "Year": 2016,
    "Method": "massey",
    "Weight": "sigmoid",
    "Conference": "",
    "Team": "Montana State",
    "Rating": -6.142721518988848,
    "Rank": 243
  },
  {
    "Year": 2016,
    "Method": "massey",
    "Weight": "sigmoid",
    "Conference": "",
    "Team": "Northern Kentucky",
    "Rating": -6.286879931254831,
    "Rank": 244
  },
  {
    "Year": 2016,
    "Method": "massey",
    "Weight": "sigmoid",
    "Conference": "",
    "Team": "Radford",
    "Rating": -6.287260920786332,
    "Rank": 245
  },
  {
    "Year": 2016,
    "Method": "massey",
    "Weight": "sigmoid",
    "Conference": "",
    "Team": "Bowling Green State",
    "Rating": -6.336236860566736,
    "Rank": 246
  },
  {
    "Year": 2016,
    "Method": "massey",
    "Weight": "sigmoid",
    "Conference": "",
    "Team": "Eastern Illinois",
    "Rating": -6.454290449541963,
    "Rank": 247
  },
  {
    "Year": 2016,
    "Method": "massey",
    "Weight": "sigmoid",
    "Conference": "",
    "Team": "Boston University",
    "Rating": -6.455438353109392,
    "Rank": 248
  },
  {
    "Year": 2016,
    "Method": "massey",
    "Weight": "sigmoid",
    "Conference": "",
    "Team": "Kennesaw State",
    "Rating": -6.456186672293809,
    "Rank": 249
  },
  {
    "Year": 2016,
    "Method": "massey",
    "Weight": "sigmoid",
    "Conference": "",
    "Team": "San Diego",
    "Rating": -6.541872055027799,
    "Rank": 250
  },
  {
    "Year": 2016,
    "Method": "massey",
    "Weight": "sigmoid",
    "Conference": "",
    "Team": "Canisius",
    "Rating": -6.70027567313293,
    "Rank": 251
  },
  {
    "Year": 2016,
    "Method": "massey",
    "Weight": "sigmoid",
    "Conference": "",
    "Team": "Samford",
    "Rating": -6.703898383424123,
    "Rank": 252
  },
  {
    "Year": 2016,
    "Method": "massey",
    "Weight": "sigmoid",
    "Conference": "",
    "Team": "Rutgers",
    "Rating": -6.7424198477919255,
    "Rank": 253
  },
  {
    "Year": 2016,
    "Method": "massey",
    "Weight": "sigmoid",
    "Conference": "",
    "Team": "South Dakota",
    "Rating": -6.843989465533142,
    "Rank": 254
  },
  {
    "Year": 2016,
    "Method": "massey",
    "Weight": "sigmoid",
    "Conference": "",
    "Team": "Hampton",
    "Rating": -6.863170572235783,
    "Rank": 255
  },
  {
    "Year": 2016,
    "Method": "massey",
    "Weight": "sigmoid",
    "Conference": "",
    "Team": "Kansas City",
    "Rating": -6.903980987844728,
    "Rank": 256
  },
  {
    "Year": 2016,
    "Method": "massey",
    "Weight": "sigmoid",
    "Conference": "",
    "Team": "NJIT",
    "Rating": -6.959543975375494,
    "Rank": 257
  },
  {
    "Year": 2016,
    "Method": "massey",
    "Weight": "sigmoid",
    "Conference": "",
    "Team": "Brown",
    "Rating": -7.039827199525439,
    "Rank": 258
  },
  {
    "Year": 2016,
    "Method": "massey",
    "Weight": "sigmoid",
    "Conference": "",
    "Team": "South Alabama",
    "Rating": -7.21076655335302,
    "Rank": 259
  },
  {
    "Year": 2016,
    "Method": "massey",
    "Weight": "sigmoid",
    "Conference": "",
    "Team": "Rice",
    "Rating": -7.255265635150627,
    "Rank": 260
  },
  {
    "Year": 2016,
    "Method": "massey",
    "Weight": "sigmoid",
    "Conference": "",
    "Team": "Appalachian State",
    "Rating": -7.282988084295167,
    "Rank": 261
  },
  {
    "Year": 2016,
    "Method": "massey",
    "Weight": "sigmoid",
    "Conference": "",
    "Team": "Western Illinois",
    "Rating": -7.468164160187097,
    "Rank": 262
  },
  {
    "Year": 2016,
    "Method": "massey",
    "Weight": "sigmoid",
    "Conference": "",
    "Team": "Portland State",
    "Rating": -7.511793437995154,
    "Rank": 263
  },
  {
    "Year": 2016,
    "Method": "massey",
    "Weight": "sigmoid",
    "Conference": "",
    "Team": "Arkansas State",
    "Rating": -7.886231969894112,
    "Rank": 264
  },
  {
    "Year": 2016,
    "Method": "massey",
    "Weight": "sigmoid",
    "Conference": "",
    "Team": "North Texas",
    "Rating": -8.057730969715701,
    "Rank": 265
  },
  {
    "Year": 2016,
    "Method": "massey",
    "Weight": "sigmoid",
    "Conference": "",
    "Team": "Colgate",
    "Rating": -8.103699107808735,
    "Rank": 266
  },
  {
    "Year": 2016,
    "Method": "massey",
    "Weight": "sigmoid",
    "Conference": "",
    "Team": "Southern",
    "Rating": -8.141454835637706,
    "Rank": 267
  },
  {
    "Year": 2016,
    "Method": "massey",
    "Weight": "sigmoid",
    "Conference": "",
    "Team": "Fairleigh Dickinson",
    "Rating": -8.226908202179402,
    "Rank": 268
  },
  {
    "Year": 2016,
    "Method": "massey",
    "Weight": "sigmoid",
    "Conference": "",
    "Team": "Liberty",
    "Rating": -8.344227648599196,
    "Rank": 269
  },
  {
    "Year": 2016,
    "Method": "massey",
    "Weight": "sigmoid",
    "Conference": "",
    "Team": "St. Francis (NY)",
    "Rating": -8.549730982444078,
    "Rank": 270
  },
  {
    "Year": 2016,
    "Method": "massey",
    "Weight": "sigmoid",
    "Conference": "",
    "Team": "Stetson",
    "Rating": -8.588654633343836,
    "Rank": 271
  },
  {
    "Year": 2016,
    "Method": "massey",
    "Weight": "sigmoid",
    "Conference": "",
    "Team": "Idaho State",
    "Rating": -8.634085182519422,
    "Rank": 272
  },
  {
    "Year": 2016,
    "Method": "massey",
    "Weight": "sigmoid",
    "Conference": "",
    "Team": "Delaware",
    "Rating": -8.671017640617581,
    "Rank": 273
  },
  {
    "Year": 2016,
    "Method": "massey",
    "Weight": "sigmoid",
    "Conference": "",
    "Team": "Mount St. Mary's",
    "Rating": -8.792253402672806,
    "Rank": 274
  },
  {
    "Year": 2016,
    "Method": "massey",
    "Weight": "sigmoid",
    "Conference": "",
    "Team": "Cal State Fullerton",
    "Rating": -8.807123037177364,
    "Rank": 275
  },
  {
    "Year": 2016,
    "Method": "massey",
    "Weight": "sigmoid",
    "Conference": "",
    "Team": "Cornell",
    "Rating": -8.901272435356173,
    "Rank": 276
  },
  {
    "Year": 2016,
    "Method": "massey",
    "Weight": "sigmoid",
    "Conference": "",
    "Team": "Army",
    "Rating": -8.942626600399318,
    "Rank": 277
  },
  {
    "Year": 2016,
    "Method": "massey",
    "Weight": "sigmoid",
    "Conference": "",
    "Team": "Utah Valley",
    "Rating": -9.095253467925996,
    "Rank": 278
  },
  {
    "Year": 2016,
    "Method": "massey",
    "Weight": "sigmoid",
    "Conference": "",
    "Team": "Longwood",
    "Rating": -9.097784544160074,
    "Rank": 279
  },
  {
    "Year": 2016,
    "Method": "massey",
    "Weight": "sigmoid",
    "Conference": "",
    "Team": "Jacksonville",
    "Rating": -9.192398036322071,
    "Rank": 280
  },
  {
    "Year": 2016,
    "Method": "massey",
    "Weight": "sigmoid",
    "Conference": "",
    "Team": "Bradley",
    "Rating": -9.243869218093796,
    "Rank": 281
  },
  {
    "Year": 2016,
    "Method": "massey",
    "Weight": "sigmoid",
    "Conference": "",
    "Team": "Quinnipiac",
    "Rating": -9.270560009796236,
    "Rank": 282
  },
  {
    "Year": 2016,
    "Method": "massey",
    "Weight": "sigmoid",
    "Conference": "",
    "Team": "Sacred Heart",
    "Rating": -9.429226948723318,
    "Rank": 283
  },
  {
    "Year": 2016,
    "Method": "massey",
    "Weight": "sigmoid",
    "Conference": "",
    "Team": "South Carolina State",
    "Rating": -9.502206033069516,
    "Rank": 284
  },
  {
    "Year": 2016,
    "Method": "massey",
    "Weight": "sigmoid",
    "Conference": "",
    "Team": "Cleveland State",
    "Rating": -9.506153492591435,
    "Rank": 285
  },
  {
    "Year": 2016,
    "Method": "massey",
    "Weight": "sigmoid",
    "Conference": "",
    "Team": "Incarnate Word",
    "Rating": -9.570328235540888,
    "Rank": 286
  },
  {
    "Year": 2016,
    "Method": "massey",
    "Weight": "sigmoid",
    "Conference": "",
    "Team": "Seattle",
    "Rating": -9.612001518923206,
    "Rank": 287
  },
  {
    "Year": 2016,
    "Method": "massey",
    "Weight": "sigmoid",
    "Conference": "",
    "Team": "Florida Atlantic",
    "Rating": -9.63703097600964,
    "Rank": 288
  },
  {
    "Year": 2016,
    "Method": "massey",
    "Weight": "sigmoid",
    "Conference": "",
    "Team": "Southern Mississippi",
    "Rating": -9.645183272002235,
    "Rank": 289
  },
  {
    "Year": 2016,
    "Method": "massey",
    "Weight": "sigmoid",
    "Conference": "",
    "Team": "Long Island University",
    "Rating": -9.953907562961168,
    "Rank": 290
  },
  {
    "Year": 2016,
    "Method": "massey",
    "Weight": "sigmoid",
    "Conference": "",
    "Team": "Lipscomb",
    "Rating": -10.122855228062424,
    "Rank": 291
  },
  {
    "Year": 2016,
    "Method": "massey",
    "Weight": "sigmoid",
    "Conference": "",
    "Team": "Holy Cross",
    "Rating": -10.199954025017696,
    "Rank": 292
  },
  {
    "Year": 2016,
    "Method": "massey",
    "Weight": "sigmoid",
    "Conference": "",
    "Team": "Sacramento State",
    "Rating": -10.25801052319508,
    "Rank": 293
  },
  {
    "Year": 2016,
    "Method": "massey",
    "Weight": "sigmoid",
    "Conference": "",
    "Team": "Morgan State",
    "Rating": -10.33640526143822,
    "Rank": 294
  },
  {
    "Year": 2016,
    "Method": "massey",
    "Weight": "sigmoid",
    "Conference": "",
    "Team": "Campbell",
    "Rating": -10.396615096673328,
    "Rank": 295
  },
  {
    "Year": 2016,
    "Method": "massey",
    "Weight": "sigmoid",
    "Conference": "",
    "Team": "Jackson State",
    "Rating": -10.417412394325982,
    "Rank": 296
  },
  {
    "Year": 2016,
    "Method": "massey",
    "Weight": "sigmoid",
    "Conference": "",
    "Team": "Youngstown State",
    "Rating": -10.569701171350404,
    "Rank": 297
  },
  {
    "Year": 2016,
    "Method": "massey",
    "Weight": "sigmoid",
    "Conference": "",
    "Team": "Marist",
    "Rating": -10.60158034491822,
    "Rank": 298
  },
  {
    "Year": 2016,
    "Method": "massey",
    "Weight": "sigmoid",
    "Conference": "",
    "Team": "Jacksonville State",
    "Rating": -10.776709451911929,
    "Rank": 299
  },
  {
    "Year": 2016,
    "Method": "massey",
    "Weight": "sigmoid",
    "Conference": "",
    "Team": "Niagara",
    "Rating": -10.89099603060884,
    "Rank": 300
  },
  {
    "Year": 2016,
    "Method": "massey",
    "Weight": "sigmoid",
    "Conference": "",
    "Team": "Houston Christian",
    "Rating": -10.941891492613363,
    "Rank": 301
  },
  {
    "Year": 2016,
    "Method": "massey",
    "Weight": "sigmoid",
    "Conference": "",
    "Team": "Loyola (MD)",
    "Rating": -10.986699566768456,
    "Rank": 302
  },
  {
    "Year": 2016,
    "Method": "massey",
    "Weight": "sigmoid",
    "Conference": "",
    "Team": "American",
    "Rating": -11.112103221850894,
    "Rank": 303
  },
  {
    "Year": 2016,
    "Method": "massey",
    "Weight": "sigmoid",
    "Conference": "",
    "Team": "Southern Illinois-Edwardsville",
    "Rating": -11.118117332374888,
    "Rank": 304
  },
  {
    "Year": 2016,
    "Method": "massey",
    "Weight": "sigmoid",
    "Conference": "",
    "Team": "Charleston Southern",
    "Rating": -11.14750315892432,
    "Rank": 305
  },
  {
    "Year": 2016,
    "Method": "massey",
    "Weight": "sigmoid",
    "Conference": "",
    "Team": "Troy",
    "Rating": -11.15242558815626,
    "Rank": 306
  },
  {
    "Year": 2016,
    "Method": "massey",
    "Weight": "sigmoid",
    "Conference": "",
    "Team": "Northern Colorado",
    "Rating": -11.2335450386155,
    "Rank": 307
  },
  {
    "Year": 2016,
    "Method": "massey",
    "Weight": "sigmoid",
    "Conference": "",
    "Team": "Robert Morris",
    "Rating": -11.570258245933978,
    "Rank": 308
  },
  {
    "Year": 2016,
    "Method": "massey",
    "Weight": "sigmoid",
    "Conference": "",
    "Team": "Alcorn State",
    "Rating": -11.826069503182012,
    "Rank": 309
  },
  {
    "Year": 2016,
    "Method": "massey",
    "Weight": "sigmoid",
    "Conference": "",
    "Team": "Illinois-Chicago",
    "Rating": -11.872281566637255,
    "Rank": 310
  },
  {
    "Year": 2016,
    "Method": "massey",
    "Weight": "sigmoid",
    "Conference": "",
    "Team": "VMI",
    "Rating": -11.87732223460874,
    "Rank": 311
  },
  {
    "Year": 2016,
    "Method": "massey",
    "Weight": "sigmoid",
    "Conference": "",
    "Team": "Saint Francis (PA)",
    "Rating": -11.898536281049436,
    "Rank": 312
  },
  {
    "Year": 2016,
    "Method": "massey",
    "Weight": "sigmoid",
    "Conference": "",
    "Team": "Alabama State",
    "Rating": -11.999414537432946,
    "Rank": 313
  },
  {
    "Year": 2016,
    "Method": "massey",
    "Weight": "sigmoid",
    "Conference": "",
    "Team": "Hartford",
    "Rating": -12.134421531396658,
    "Rank": 314
  },
  {
    "Year": 2016,
    "Method": "massey",
    "Weight": "sigmoid",
    "Conference": "",
    "Team": "Massachusetts-Lowell",
    "Rating": -12.31137651013278,
    "Rank": 315
  },
  {
    "Year": 2016,
    "Method": "massey",
    "Weight": "sigmoid",
    "Conference": "",
    "Team": "Binghamton",
    "Rating": -12.332838360389768,
    "Rank": 316
  },
  {
    "Year": 2016,
    "Method": "massey",
    "Weight": "sigmoid",
    "Conference": "",
    "Team": "North Carolina Central",
    "Rating": -12.622218333424051,
    "Rank": 317
  },
  {
    "Year": 2016,
    "Method": "massey",
    "Weight": "sigmoid",
    "Conference": "",
    "Team": "Presbyterian",
    "Rating": -12.760352064989103,
    "Rank": 318
  },
  {
    "Year": 2016,
    "Method": "massey",
    "Weight": "sigmoid",
    "Conference": "",
    "Team": "Maryland-Eastern Shore",
    "Rating": -12.773531646436272,
    "Rank": 319
  },
  {
    "Year": 2016,
    "Method": "massey",
    "Weight": "sigmoid",
    "Conference": "",
    "Team": "Bethune-Cookman",
    "Rating": -12.893793498037226,
    "Rank": 320
  },
  {
    "Year": 2016,
    "Method": "massey",
    "Weight": "sigmoid",
    "Conference": "",
    "Team": "Abilene Christian",
    "Rating": -13.006718110051532,
    "Rank": 321
  },
  {
    "Year": 2016,
    "Method": "massey",
    "Weight": "sigmoid",
    "Conference": "",
    "Team": "Southeastern Louisiana",
    "Rating": -13.171708256284669,
    "Rank": 322
  },
  {
    "Year": 2016,
    "Method": "massey",
    "Weight": "sigmoid",
    "Conference": "",
    "Team": "Lafayette",
    "Rating": -13.798457703447404,
    "Rank": 323
  },
  {
    "Year": 2016,
    "Method": "massey",
    "Weight": "sigmoid",
    "Conference": "",
    "Team": "South Carolina Upstate",
    "Rating": -13.903009918686992,
    "Rank": 324
  },
  {
    "Year": 2016,
    "Method": "massey",
    "Weight": "sigmoid",
    "Conference": "",
    "Team": "Southeast Missouri State",
    "Rating": -14.268358609714742,
    "Rank": 325
  },
  {
    "Year": 2016,
    "Method": "massey",
    "Weight": "sigmoid",
    "Conference": "",
    "Team": "Coppin State",
    "Rating": -14.441707000431173,
    "Rank": 326
  },
  {
    "Year": 2016,
    "Method": "massey",
    "Weight": "sigmoid",
    "Conference": "",
    "Team": "UTSA",
    "Rating": -14.472710477798485,
    "Rank": 327
  },
  {
    "Year": 2016,
    "Method": "massey",
    "Weight": "sigmoid",
    "Conference": "",
    "Team": "Nicholls State",
    "Rating": -14.592767073299331,
    "Rank": 328
  },
  {
    "Year": 2016,
    "Method": "massey",
    "Weight": "sigmoid",
    "Conference": "",
    "Team": "Savannah State",
    "Rating": -14.83086163033055,
    "Rank": 329
  },
  {
    "Year": 2016,
    "Method": "massey",
    "Weight": "sigmoid",
    "Conference": "",
    "Team": "Northwestern State",
    "Rating": -14.852267609699876,
    "Rank": 330
  },
  {
    "Year": 2016,
    "Method": "massey",
    "Weight": "sigmoid",
    "Conference": "",
    "Team": "Central Arkansas",
    "Rating": -14.91301409762404,
    "Rank": 331
  },
  {
    "Year": 2016,
    "Method": "massey",
    "Weight": "sigmoid",
    "Conference": "",
    "Team": "Alabama A&M",
    "Rating": -15.227310187191575,
    "Rank": 332
  },
  {
    "Year": 2016,
    "Method": "massey",
    "Weight": "sigmoid",
    "Conference": "",
    "Team": "New Orleans",
    "Rating": -15.281608303305608,
    "Rank": 333
  },
  {
    "Year": 2016,
    "Method": "massey",
    "Weight": "sigmoid",
    "Conference": "",
    "Team": "Maryland-Baltimore County",
    "Rating": -16.058841714439623,
    "Rank": 334
  },
  {
    "Year": 2016,
    "Method": "massey",
    "Weight": "sigmoid",
    "Conference": "",
    "Team": "The Citadel",
    "Rating": -16.064333550366385,
    "Rank": 335
  },
  {
    "Year": 2016,
    "Method": "massey",
    "Weight": "sigmoid",
    "Conference": "",
    "Team": "McNeese State",
    "Rating": -16.095136917317905,
    "Rank": 336
  },
  {
    "Year": 2016,
    "Method": "massey",
    "Weight": "sigmoid",
    "Conference": "",
    "Team": "Prairie View",
    "Rating": -16.4280741504136,
    "Rank": 337
  },
  {
    "Year": 2016,
    "Method": "massey",
    "Weight": "sigmoid",
    "Conference": "",
    "Team": "Lamar",
    "Rating": -16.585128633812275,
    "Rank": 338
  },
  {
    "Year": 2016,
    "Method": "massey",
    "Weight": "sigmoid",
    "Conference": "",
    "Team": "Howard",
    "Rating": -16.706760401412073,
    "Rank": 339
  },
  {
    "Year": 2016,
    "Method": "massey",
    "Weight": "sigmoid",
    "Conference": "",
    "Team": "Southern Utah",
    "Rating": -17.30658284812411,
    "Rank": 340
  },
  {
    "Year": 2016,
    "Method": "massey",
    "Weight": "sigmoid",
    "Conference": "",
    "Team": "North Carolina A&T",
    "Rating": -17.337818173643846,
    "Rank": 341
  },
  {
    "Year": 2016,
    "Method": "massey",
    "Weight": "sigmoid",
    "Conference": "",
    "Team": "Maine",
    "Rating": -17.37531982988586,
    "Rank": 342
  },
  {
    "Year": 2016,
    "Method": "massey",
    "Weight": "sigmoid",
    "Conference": "",
    "Team": "Texas-Rio Grande Valley",
    "Rating": -18.00556834484591,
    "Rank": 343
  },
  {
    "Year": 2016,
    "Method": "massey",
    "Weight": "sigmoid",
    "Conference": "",
    "Team": "Bryant",
    "Rating": -18.163086565494908,
    "Rank": 344
  },
  {
    "Year": 2016,
    "Method": "massey",
    "Weight": "sigmoid",
    "Conference": "",
    "Team": "Northern Arizona",
    "Rating": -18.583706298442006,
    "Rank": 345
  },
  {
    "Year": 2016,
    "Method": "massey",
    "Weight": "sigmoid",
    "Conference": "",
    "Team": "Mississippi Valley State",
    "Rating": -18.602718564028784,
    "Rank": 346
  },
  {
    "Year": 2016,
    "Method": "massey",
    "Weight": "sigmoid",
    "Conference": "",
    "Team": "Arkansas-Pine Bluff",
    "Rating": -18.82375477634729,
    "Rank": 347
  },
  {
    "Year": 2016,
    "Method": "massey",
    "Weight": "sigmoid",
    "Conference": "",
    "Team": "Grambling",
    "Rating": -18.899870918767483,
    "Rank": 348
  },
  {
    "Year": 2016,
    "Method": "massey",
    "Weight": "sigmoid",
    "Conference": "",
    "Team": "Chicago State",
    "Rating": -18.987085133154665,
    "Rank": 349
  },
  {
    "Year": 2016,
    "Method": "massey",
    "Weight": "sigmoid",
    "Conference": "",
    "Team": "Delaware State",
    "Rating": -19.1822837677608,
    "Rank": 350
  },
  {
    "Year": 2016,
    "Method": "massey",
    "Weight": "sigmoid",
    "Conference": "",
    "Team": "Central Connecticut State",
    "Rating": -19.656485709386693,
    "Rank": 351
  },
  {
    "Year": 2016,
    "Method": "massey",
    "Weight": "sigmoid",
    "Conference": "",
    "Team": "Florida A&M",
    "Rating": -21.363802835848944,
    "Rank": 352
  }
]