[
  {
    "Year": 2018,
    "Method": "massey",
    "Weight": "logarithmic",
    "Conference": "MAC",
    "Team": "Buffalo",
    "Rating": 11.244200874167504,
    "Rank": 1
  },
  {
    "Year": 2018,
    "Method": "massey",
    "Weight": "logarithmic",
    "Conference": "MAC",
    "Team": "Toledo",
    "Rating": 5.221999957412501,
    "Rank": 2
  },
  {
    "Year": 2018,
    "Method": "massey",
    "Weight": "logarithmic",
    "Conference": "MAC",
    "Team": "Eastern Michigan",
    "Rating": 3.949496808813708,
    "Rank": 3
  },
  {
    "Year": 2018,
    "Method": "massey",
    "Weight": "logarithmic",
    "Conference": "MAC",
    "Team": "Miami (OH)",
    "Rating": 0.8788949504887572,
    "Rank": 4
  },
  {
    "Year": 2018,
    "Method": "massey",
    "Weight": "logarithmic",
    "Conference": "MAC",
    "Team": "Central Michigan",
    "Rating": 0.5526709690811301,
    "Rank": 5
  },
  {
    "Year": 2018,
    "Method": "massey",
    "Weight": "logarithmic",
    "Conference": "MAC",
    "Team": "Ball State",
    "Rating": -0.5815932950753377,
    "Rank": 6
  },
  {
    "Year": 2018,
    "Method": "massey",
    "Weight": "logarithmic",
    "Conference": "MAC",
    "Team": "Western Michigan",
    "Rating": -0.9566408169614428,
    "Rank": 7
  },
  {
    "Year": 2018,
    "Method": "massey",
    "Weight": "logarithmic",
    "Conference": "MAC",
    "Team": "Ohio",
    "Rating": -1.9925279730324936,
    "Rank": 8
  },
  {
    "Year": 2018,
    "Method": "massey",
    "Weight": "logarithmic",
    "Conference": "MAC",
    "Team": "Kent State",
    "Rating": -2.041386086852853,
    "Rank": 9
  },
  {
    "Year": 2018,
    "Method": "massey",
    "Weight": "logarithmic",
    "Conference": "MAC",
    "Team": "Bowling Green State",
    "Rating": -4.867681134123672,
    "Rank": 10
  },
  {
    "Year": 2018,
    "Method": "massey",
    "Weight": "logarithmic",
    "Conference": "MAC",
    "Team": "Akron",
    "Rating": -5.397680130030787,
    "Rank": 11
  },
  {
    "Year": 2018,
    "Method": "massey",
    "Weight": "logarithmic",
    "Conference": "MAC",
    "Team": "Northern Illinois",
    "Rating": -6.009754123887046,
    "Rank": 12
  }
]