[
  {
    "Year": 2025,
    "Method": "massey",
    "Weight": "logarithmic",
    "Conference": "Ivy",
    "Team": "Yale",
    "Rating": 10.271959722894357,
    "Rank": 1
  },
  {
    "Year": 2025,
    "Method": "massey",
    "Weight": "logarithmic",
    "Conference": "Ivy",
    "Team": "Cornell",
    "Rating": 6.69898637317904,
    "Rank": 2
  },
  {
    "Year": 2025,
    "Method": "massey",
    "Weight": "logarithmic",
    "Conference": "Ivy",
    "Team": "Dartmouth",
    "Rating": 3.897388798829544,
    "Rank": 3
  },
  {
    "Year": 2025,
    "Method": "massey",
    "Weight": "logarithmic",
    "Conference": "Ivy",
    "Team": "Brown",
    "Rating": -0.904724805122426,
    "Rank": 4
  },
  {
    "Year": 2025,
    "Method": "massey",
    "Weight": "logarithmic",
    "Conference": "Ivy",
    "Team": "Harvard",
    "Rating": -1.83318460442739,
    "Rank": 5
  },
  {
    "Year": 2025,
    "Method": "massey",
    "Weight": "logarithmic",
    "Conference": "Ivy",
    "Team": "Princeton",
    "Rating": -1.9925317333726456,
    "Rank": 6
  },
  {
    "Year": 2025,
    "Method": "massey",
    "Weight": "logarithmic",
    "Conference": "Ivy",
    "Team": "Pennsylvania",
    "Rating": -5.365162237485851,
    "Rank": 7
  },
  {
    "Year": 2025,
    "Method": "massey",
    "Weight": "logarithmic",
    "Conference": "Ivy",
    "Team": "Columbia",
    "Rating": -10.772731514494618,
    "Rank": 8
  }
]