[
  {
    "Year": 2025,
    "Method": "colley",
    "Weight": "biweekly",
    "Conference": "OVC",
    "Team": "Southeast Missouri State",
    "Rating": 0.7207096399834908,
    "Rank": 1
  },
  {
    "Year": 2025,
    "Method": "colley",
    "Weight": "biweekly",
    "Conference": "OVC",
    "Team": "Southern Illinois-Edwardsville",
    "Rating": 0.6960537731248257,
    "Rank": 2
  },
  {
    "Year": 2025,
    "Method": "colley",
    "Weight": "biweekly",
    "Conference": "OVC",
    "Team": "Tennessee State",
    "Rating": 0.6254327903448605,
    "Rank": 3
  },
  {
    "Year": 2025,
    "Method": "colley",
    "Weight": "biweekly",
    "Conference": "OVC",
    "Team": "Little Rock",
    "Rating": 0.5657559188623251,
    "Rank": 4
  },
  {
    "Year": 2025,
    "Method": "colley",
    "Weight": "biweekly",
    "Conference": "OVC",
    "Team": "Lindenwood",
    "Rating": 0.5068039539629323,
    "Rank": 5
  },
  {
    "Year": 2025,
    "Method": "colley",
    "Weight": "biweekly",
    "Conference": "OVC",
    "Team": "SIU Edwardsville",
    "Rating": 0.5,
    "Rank": 6
  },
  {
    "Year": 2025,
    "Method": "colley",
    "Weight": "biweekly",
    "Conference": "OVC",
    "Team": "Tennessee Tech",
    "Rating": 0.4584165548398283,
    "Rank": 7
  },
  {
    "Year": 2025,
    "Method": "colley",
    "Weight": "biweekly",
    "Conference": "OVC",
    "Team": "Eastern Illinois",
    "Rating": 0.4579505893787647,
    "Rank": 8
  },
  {
    "Year": 2025,
    "Method": "colley",
    "Weight": "biweekly",
    "Conference": "OVC",
    "Team": "Tennessee-Martin",
    "Rating": 0.4522303525326006,
    "Rank": 9
  },
  {
    "Year": 2025,
    "Method": "colley",
    "Weight": "biweekly",
    "Conference": "OVC",
    "Team": "Morehead State",
    "Rating": 0.4073184676107063,
    "Rank": 10
  },
  {
    "Year": 2025,
    "Method": "colley",
    "Weight": "biweekly",
    "Conference": "OVC",
    "Team": "Western Illinois",
    "Rating": 0.343246665485613,
    "Rank": 11
  },
  {
    "Year": 2025,
    "Method": "colley",
    "Weight": "biweekly",
    "Conference": "OVC",
    "Team": "Southern Indiana",
    "Rating": 0.266081293874057,
    "Rank": 12
  }
]